LICENSE
pokerlib/__init__.py
pokerlib/_handparser.py
pokerlib/_player.py
pokerlib/_round.py
pokerlib/_table.py
pokerlib/enums.py
pokerlib/implementations/__init__.py
pokerlib/implementations/_no_muck_showdown_table.py
pokerlib/implementations/_no_muck_table.py
pokerlib-2.2.6.dist-info/LICENSE
pokerlib-2.2.6.dist-info/METADATA
pokerlib-2.2.6.dist-info/WHEEL
pokerlib-2.2.6.dist-info/RECORD
