Metadata-Version: 2.1
Name: pokerlib
Version: 2.2.6
Summary: Python poker library
Home-page: https://github.com/kuco23/pokerlib/
Keywords: python,poker,library
Author: kuco23
Author-email: nseverkar@gmail.com
Requires-Python: >=3.10,<4.0
Classifier: Development Status :: 3 - Alpha
Classifier: Intended Audience :: Developers
Classifier: License :: Free For Home Use
Classifier: Programming Language :: Python :: 3
Classifier: Programming Language :: Python :: 3.10
Classifier: Programming Language :: Python :: 3.11
Classifier: Programming Language :: Python :: 3
Classifier: Topic :: Software Development :: Build Tools
Project-URL: Repository, https://github.com/kuco23/pokerlib/
